gl_client_py-0.1.7.dist-info/METADATA
gl_client_py-0.1.7.dist-info/WHEEL
glclient/glclient.pyi
glclient/greenlight_pb2.pyi
glclient/__init__.py
glclient/scheduler_pb2.pyi
glclient/__pycache__/__init__.cpython-38.pyc
glclient/__pycache__/greenlight_pb2.cpython-38.pyc
glclient/__pycache__/scheduler_pb2.cpython-38.pyc
glclient/__pycache__/tls.cpython-310.pyc
glclient/__pycache__/node_pb2.cpython-310.pyc
glclient/__pycache__/scheduler_pb2_grpc.cpython-310.pyc
glclient/__pycache__/greenlight_pb2_grpc.cpython-310.pyc
glclient/__pycache__/greenlight_pb2.cpython-310.pyc
glclient/__pycache__/scheduler_pb2.cpython-310.pyc
glclient/__pycache__/node_pb2.cpython-38.pyc
glclient/__pycache__/__init__.cpython-310.pyc
glclient/tls.py
glclient/rpc.py
glclient/greenlight_pb2_grpc.pyi
glclient/node_pb2_grpc.py
glclient/scheduler_pb2_grpc.py
glclient/greenlight_pb2.py
glclient/greenlight_pb2_grpc.py
glclient/scheduler_pb2.py
glclient/node_pb2.py
glclient/glclient.abi3.so
gl_client_py-0.1.7.dist-info/RECORD
