Metadata-Version: 2.1
Name: gl-client-py
Version: 0.1.7
Requires-Dist: protobuf>=3
